Workbook
Name aporte: capital_invest!$D$18
Name periodo_em_anos: capital_invest!$D$19
Name qnt_quero_investir: capital_invest!$D$18
Name rendimento_carteira: capital_invest!$D$13
Name sugestao_aporte: capital_invest!$D$14
Name sugestao_investimento: capital_invest!$D$14
Name taxa_rendimento_mensal: capital_invest!$D$20

Sheet capital_invest
B11: CONFIGURAÇÃO
B12: Salário | D12: 1600
B13: Rendimento Carteira | D13: 0.0089
B14: Sugestão de Investimento (30%) | D14: =$D$12*30% -> 480
B17: INVESTIMENTO MENSAL
B18: Quanto quero investir por mês | D18: 480
B19: Período em anos | D19: 2
B20: Taxa de rendimento mensal | D20: 0.01075
B21: Patrímonio acumulado | D21: =FV(taxa_rendimento_mensal,periodo_em_anos*12,aporte*-1) -> 13063.05
B22: Dividendos Mensais | D22: =D21*taxa_rendimento_mensal -> 140.42778
B25: CENÁRIOS | C25: PATRIMÔNIO | D25: DIVIDENDO
B26: Quanto em 2 anos eu teria | C26: =FV(taxa_rendimento_mensal,2*12,aporte*-1) -> 13063.05 | D26: =C26*taxa_rendimento_mensal -> 140.42778
B27: Quanto em 5 anos eu teria | C27: =FV(taxa_rendimento_mensal,5*12,aporte*-1) -> 40160.929 | D27: =C27*taxa_rendimento_mensal -> 431.72998
B28: Quanto em 10 anos eu teria | C28: =FV(taxa_rendimento_mensal,10*12,aporte*-1) -> 116444.1 | D28: =C28*taxa_rendimento_mensal -> 1251.7741
B29: Quanto em 20 anos eu teria | C29: =FV(taxa_rendimento_mensal,20*12,aporte*-1) -> 536558.43 | D29: =C29*taxa_rendimento_mensal -> 5768.0031
B30: Quanto em 30 anos eu teria | C30: =FV(taxa_rendimento_mensal,30*12,aporte*-1) -> 2052273.2 | D30: =C30*taxa_rendimento_mensal -> 22061.937
B33: Perfil de Investidor | D33: Conservador
B34: Valor a ser investido mensalmente | D34: =aporte -> 480
B36: Tipo de FII | C36: Percentual Sugerido | D36: Valores
B37: Papel | C37: =VLOOKUP($D$33&"-"&B37, Apoio!$A:$D,4,0) -> 0.2 | D37: =C37*aporte -> 96
B38: Tijolo | C38: =VLOOKUP($D$33&"-"&B38, Apoio!$A:$D,4,0) -> 0.6 | D38: =C38*aporte -> 288
B39: Híbridos | C39: =VLOOKUP($D$33&"-"&B39, Apoio!$A:$D,4,0) -> 0.1 | D39: =C39*aporte -> 48
B40: FOFs | C40: =VLOOKUP($D$33&"-"&B40, Apoio!$A:$D,4,0) -> 0.1 | D40: =C40*aporte -> 48
B41: Desenvolvimento | C41: =VLOOKUP($D$33&"-"&B41, Apoio!$A:$D,4,0) -> 0 | D41: =C41*aporte -> 0
B42: Hotelarias | C42: =VLOOKUP($D$33&"-"&B42, Apoio!$A:$D,4,0) -> 0 | D42: =C42*aporte -> 0
B43: Total | D43: =SUM(D37:E42) -> 480

Sheet Apoio
A2: Chave Composta | B2: Perfil | C2: Tipo FII | D2: %
A3: =B3&"-"&C3 -> Conservador-Papel | B3: Conservador | C3: Papel | D3: 0.2
A4: =B4&"-"&C4 -> Conservador-Tijolo | B4: Conservador | C4: Tijolo | D4: 0.6
A5: =B5&"-"&C5 -> Conservador-Híbridos | B5: Conservador | C5: Híbridos | D5: 0.1
A6: =B6&"-"&C6 -> Conservador-FOFs | B6: Conservador | C6: FOFs | D6: 0.1
A7: =B7&"-"&C7 -> Conservador-Desenvolvimento | B7: Conservador | C7: Desenvolvimento | D7: 0
A8: =B8&"-"&C8 -> Conservador-Hotelarias | B8: Conservador | C8: Hotelarias | D8: 0
A9: =B9&"-"&C9 -> Moderado-Papel | B9: Moderado | C9: Papel | D9: 0.3
A10: =B10&"-"&C10 -> Moderado-Tijolo | B10: Moderado | C10: Tijolo | D10: 0.45
A11: =B11&"-"&C11 -> Moderado-Híbridos | B11: Moderado | C11: Híbridos | D11: 0.1
A12: =B12&"-"&C12 -> Moderado-FOFs | B12: Moderado | C12: FOFs | D12: 0.05
A13: =B13&"-"&C13 -> Moderado-Desenvolvimento | B13: Moderado | C13: Desenvolvimento | D13: 0.05
A14: =B14&"-"&C14 -> Moderado-Hotelarias | B14: Moderado | C14: Hotelarias | D14: 0.05
... A20: =B20&"-"&C20 -> Agressivo-Hotelarias | B20: Agressivo | C20: Hotelarias | D20: 0.1
